MANIFEST.in
README.md
setup.py
dash_admin_components/Body.py
dash_admin_components/Box.py
dash_admin_components/BoxBody.py
dash_admin_components/BoxDropdown.py
dash_admin_components/BoxDropdownDivider.py
dash_admin_components/BoxDropdownItem.py
dash_admin_components/BoxFooter.py
dash_admin_components/BoxHeader.py
dash_admin_components/Controlbar.py
dash_admin_components/Footer.py
dash_admin_components/Icon.py
dash_admin_components/InfoBox.py
dash_admin_components/Navbar.py
dash_admin_components/NavbarDropdown.py
dash_admin_components/NavbarDropdownItem.py
dash_admin_components/Page.py
dash_admin_components/Sidebar.py
dash_admin_components/SidebarButton.py
dash_admin_components/SidebarHeader.py
dash_admin_components/SidebarMenu.py
dash_admin_components/SidebarMenuItem.py
dash_admin_components/SidebarMenuSubItem.py
dash_admin_components/SimpleBox.py
dash_admin_components/TabBox.py
dash_admin_components/TabBoxBody.py
dash_admin_components/TabBoxHeader.py
dash_admin_components/TabBoxMenu.py
dash_admin_components/TabBoxMenuItem.py
dash_admin_components/TabItem.py
dash_admin_components/TabItems.py
dash_admin_components/UserCard.py
dash_admin_components/ValueBox.py
dash_admin_components/__init__.py
dash_admin_components/_imports_.py
dash_admin_components/admindash.css
dash_admin_components/adminlte.css
dash_admin_components/dash_admin_components.dev.js
dash_admin_components/dash_admin_components.min.js
dash_admin_components/metadata.json
dash_admin_components/package.json
dash_admin_components.egg-info/PKG-INFO
dash_admin_components.egg-info/SOURCES.txt
dash_admin_components.egg-info/dependency_links.txt
dash_admin_components.egg-info/top_level.txt