Metadata-Version: 1.0
Name: dash-admin-components
Version: 0.0.9
Summary: AdminLTE3 component suite for Dash
Home-page: UNKNOWN
Author: Dawid Kopczyk <dawid.kopczyk@quantee.ai>
Author-email: UNKNOWN
License: MIT
Platform: UNKNOWN
